iconrpcserver/__init__.py
iconrpcserver/__main__.py
iconrpcserver/icon_rpcserver_app.py
iconrpcserver/icon_rpcserver_cli.py
iconrpcserver/components/__init__.py
iconrpcserver/components/singleton.py
iconrpcserver/default_conf/__init__.py
iconrpcserver/default_conf/icon_rpcserver_config.py
iconrpcserver/default_conf/icon_rpcserver_constant.py
iconrpcserver/dispatcher/__init__.py
iconrpcserver/dispatcher/exception.py
iconrpcserver/dispatcher/validator.py
iconrpcserver/dispatcher/default/__init__.py
iconrpcserver/dispatcher/default/node.py
iconrpcserver/dispatcher/default/websocket.py
iconrpcserver/dispatcher/v2/__init__.py
iconrpcserver/dispatcher/v2/version2.py
iconrpcserver/dispatcher/v3/__init__.py
iconrpcserver/dispatcher/v3/icx.py
iconrpcserver/dispatcher/v3/ise.py
iconrpcserver/dispatcher/v3/rep.py
iconrpcserver/dispatcher/v3/version3.py
iconrpcserver/dispatcher/v3d/__init__.py
iconrpcserver/dispatcher/v3d/version3d.py
iconrpcserver/server/__init__.py
iconrpcserver/server/rest_server.py
iconrpcserver/utils/__init__.py
iconrpcserver/utils/json_rpc.py
iconrpcserver/utils/message_code.py
iconrpcserver/utils/icon_service/__init__.py
iconrpcserver/utils/icon_service/converter.py
iconrpcserver/utils/icon_service/templates.py
iconrpcserver/utils/message_queue/__init__.py
iconrpcserver/utils/message_queue/channel_inner_stub.py
iconrpcserver/utils/message_queue/icon_score_inner_stub.py
iconrpcserver/utils/message_queue/peer_inner_stub.py
iconrpcserver/utils/message_queue/stub_collection.py
iconrpcserver-1.7.2.dist-info/LICENSE
iconrpcserver-1.7.2.dist-info/METADATA
iconrpcserver-1.7.2.dist-info/WHEEL
iconrpcserver-1.7.2.dist-info/entry_points.txt
iconrpcserver-1.7.2.dist-info/top_level.txt
iconrpcserver-1.7.2.dist-info/RECORD
