Metadata-Version: 2.1
Name: iconrpcserver
Version: 1.7.2
Summary: ICON RPC Server
Home-page: https://github.com/icon-project/icon-rpc-server
Author: ICON Foundation
Author-email: foo@icon.foundation
License: Apache License 2.0
Platform: UNKNOWN
Classifier: Development Status :: 5 - Production/Stable
Classifier: Intended Audience :: Developers
Classifier: Intended Audience :: System Administrators
Classifier: Natural Language :: English
Classifier: License :: OSI Approved :: Apache Software License
Classifier: Programming Language :: Python
Classifier: Programming Language :: Python :: 3.7
Classifier: Programming Language :: Python :: 3 :: Only
License-File: LICENSE
Requires-Dist: aiohttp (<=3.7.4)
Requires-Dist: jsonschema (~=3.2.0)
Requires-Dist: jsonrpcserver (~=4.1.2)
Requires-Dist: jsonrpcclient[aiohttp] (~=3.3.5)
Requires-Dist: websockets (~=9.1.0)
Requires-Dist: sanic (~=21.6.0)
Requires-Dist: gunicorn (~=20.0.0)
Requires-Dist: sanic-cors (~=1.0.0)
Requires-Dist: earlgrey (~=0.2.1)
Requires-Dist: iconcommons (~=1.1.3)
Requires-Dist: typing-extensions (~=3.7.4)
Provides-Extra: tests
Requires-Dist: pytest (~=5.4.2) ; extra == 'tests'
Requires-Dist: pytest-asyncio (~=0.12.0) ; extra == 'tests'
Requires-Dist: mock (~=4.0.1) ; extra == 'tests'
Requires-Dist: pytest-sanic (~=1.8.1) ; extra == 'tests'
